mongo_dynamic_fixture
tests
