Metadata-Version: 1.1
Name: mongo-dynamic-fixture
Version: 0.2.1
Summary: Mongo Dynamic Fixture
Home-page: https://github.com/se7entyse7en/mongo-dynamic-fixture
Author: Lou Marvin Caraig
Author-email: loumarvincaraig@gmail.com
License: MIT
Platform: UNKNOWN
Classifier: Development Status :: 4 - Beta
Classifier: Intended Audience :: Developers
Classifier: License :: OSI Approved :: MIT License
Classifier: Natural Language :: English
Classifier: Programming Language :: Python
Classifier: Programming Language :: Python :: 2
Classifier: Programming Language :: Python :: 2.7
Classifier: Programming Language :: Python :: 3
Classifier: Programming Language :: Python :: 3.3
Classifier: Programming Language :: Python :: 3.4
Classifier: Topic :: Database
Classifier: Topic :: Software Development :: Testing
